[
  {
    "title": "Dangal",
    "description": "Mahavir Singh Phogat, a former amateur wrestler    trained in the pehlwani style of Indian wrestling, was a national wrestling    champion residing in Balali. He was forced by his father to give up the    sport in order to obtain gainful employment. Dejected that he could not win    a medal for his country, he vows that his unborn son will. Disappointed upon    having four daughters, he gives up hope. But when his older daughters Geeta    and Babita come home after beating up two boys in response to derogatory comments,    he realises their potential to become wrestlers and begins coaching them. ",
    "Director": "Amir Khan",
    "stars": [
      "Amir Khan",
      "Mahavir Phogat"
    ]
  },
  {
    "title": "Mission Impossible 5",
    "description": "Ethan Hunt and his IMF team,     along with some familiar allies, race against time after a mission gone wrong.",
    "Director": "Christopher McQuarrie",
    "stars": [
      "Matthew McConaughey",
      "Anne Hathaway"
    ]
  }
]
